livecheck/__init__.py
livecheck/__main__.py
livecheck/constants.py
livecheck/main.py
livecheck/py.typed
livecheck/settings.py
livecheck/special/__init__.py
livecheck/special/bitbucket.py
livecheck/special/checksum.py
livecheck/special/composer.py
livecheck/special/davinci.py
livecheck/special/directory.py
livecheck/special/dotnet.py
livecheck/special/gist.py
livecheck/special/github.py
livecheck/special/gitlab.py
livecheck/special/golang.py
livecheck/special/gomodule.py
livecheck/special/handlers.py
livecheck/special/jetbrains.py
livecheck/special/maven.py
livecheck/special/metacpan.py
livecheck/special/nodejs.py
livecheck/special/package.py
livecheck/special/pecl.py
livecheck/special/pypi.py
livecheck/special/regex.py
livecheck/special/repology.py
livecheck/special/rubygems.py
livecheck/special/sourceforge.py
livecheck/special/sourcehut.py
livecheck/special/utils.py
livecheck/special/yarn.py
livecheck/typing.py
livecheck/utils/__init__.py
livecheck/utils/assertions.py
livecheck/utils/credentials.py
livecheck/utils/misc.py
livecheck/utils/portage.py
livecheck/utils/requests.py
livecheck/utils/string.py
livecheck-0.1.3.dist-info/LICENSE.txt
livecheck-0.1.3.dist-info/METADATA
livecheck-0.1.3.dist-info/WHEEL
livecheck-0.1.3.dist-info/entry_points.txt
livecheck-0.1.3.dist-info/RECORD
