Metadata-Version: 2.3
Name: livecheck
Version: 0.1.3
Summary: Tool to update ebuilds.
License: MIT
Keywords: command line,ebuild,gentoo,portage
Author: Andrew Udvare
Author-email: audvare@gmail.com
Requires-Python: >=3.10,<3.14
Classifier: Development Status :: 4 - Beta
Classifier: Intended Audience :: Developers
Classifier: Programming Language :: Python
Classifier: Programming Language :: Python :: 3.10
Classifier: Programming Language :: Python :: 3.11
Classifier: Programming Language :: Python :: 3.12
Classifier: Programming Language :: Python :: 3.13
Classifier: Typing :: Typed
Requires-Dist: bascom (>=0.0.1,<0.0.2)
Requires-Dist: beautifulsoup4 (>=4.13.5,<5.0.0)
Requires-Dist: click (>=8.3.0,<9.0.0)
Requires-Dist: defusedxml (>=0.7.1,<0.8.0)
Requires-Dist: html5lib (>=1.1,<2.0)
Requires-Dist: keyring (>=25.6.0,<26.0.0)
Requires-Dist: platformdirs (>=4.4.0,<5.0.0)
Requires-Dist: requests (>=2.32.5,<3.0.0)
Requires-Dist: typing-extensions (>=4.15.0,<5.0.0)
Project-URL: Documentation, https://livecheck.readthedocs.org
Project-URL: Homepage, https://tatsh.github.io/livecheck/
Project-URL: Issues, https://github.com/Tatsh/livecheck/issues
Project-URL: Repository, https://github.com/Tatsh/livecheck
